Workbook

Sheet Instruções
A1: Lista de Preços do Fornecedor — Instruções de Preenchimento
A3: Este ficheiro permite enviar-nos a sua lista de preços de forma que possa ser carregada automaticamente no sistema — sem reformatação manual — e ficar visível às farmácias.
A5: 1. Como preencher
A6: • Preencha apenas a folha "Lista de Preços". Não altere as folhas "Validação" e "Dicionário".
A7: • Não altere as linhas 1 e 2 (cabeçalhos) nem os nomes das folhas.
A8: • A linha 3 é um EXEMPLO preenchido, a título ilustrativo — apague-a antes de nos devolver o ficheiro.
A9: • Cada linha = um produto. Comece a preencher a partir da linha 4.
A10: • Para actualizar um produto já enviado antes, mantenha o mesmo "Código do Fornecedor (SKU)" — é essa coluna que o sistema usa para saber que é o mesmo produto.
A12: 2. Campos obrigatórios e opcionais
A13: Os cabeçalhos das colunas obrigatórias têm fundo amarelo claro; os opcionais têm fundo cinzento claro. A lista completa, com o significado e as regras de cada coluna, está na folha "Dicionário".
A14: Colunas obrigatórias nesta versão: Código do Fornecedor, Nome Comercial, Nome Científico (DCI), Forma Farmacêutica, Dosagem, Unidades por Embalagem, Preço à Farmácia, Preço ao Público (PVP), Estado de Stock, Moeda, Válido a partir de.
A16: 3. O que o sistema faz com cada coluna (resumo)
... A42: Dúvidas? Contacte a equipa que lhe enviou este ficheiro.

Sheet Lista de Preços
A1: Código do Fornecedor (SKU) * | B1: Nome Comercial * | C1: Nome Científico (DCI) * | D1: Forma Farmacêutica * | E1: Dosagem * | F1: Unidades por Embalagem * | G1: Unidade da Embalagem | H1: Fabricante | I1: País de Origem | J1: Número AIM | K1: Código de Barras | L1: Preço à Farmácia (MZN) * | M1: Preço ao Público / PVP (MZN) * | N1: Desconto do Fornecedor (%) | O1: Custo (Confidencial) | P1: Estado de Stock * | Q1: Quantidade Disponível | R1: Número de Lote | S1: Data de Validade | T1: Quantidade Mínima de Encomenda | U1: Moeda * | V1: Válido a partir de * | W1: Observações | Z1: LEGENDA
A2: vendor_sku | B2: product_name_brand | C2: product_name_inn | D2: form | E2: strength | F2: pack_size | G2: pack_unit | H2: manufacturer | I2: country_of_origin | J2: aim_number | K2: barcode | L2: price_to_pharmacy | M2: price_to_public | N2: discount_percent | O2: cost_to_us | P2: stock_status | Q2: available_quantity | R2: batch_number | S2: expiry_date | T2: min_order_qty | U2: currency | V2: effective_from | W2: notes | Z2: * = campo obrigatório
A3: AH-AMX500-24 | B3: Amoxil 500mg | C3: Amoxicilina | D3: Cápsula | E3: 500mg | F3: 24 | G3: cápsulas | H3: GlaxoSmithKline | I3: Índia | J3: AIM-MZ-004521 | K3: 7891234567895 | L3: 185 | M3: 249 | N3: 0.05 | O3: 150 | P3: Em stock | Q3: 120 | R3: L2026-0912 | S3: 46568 | T3: 1 | U3: MZN | V3: 46280 | W3: Promoção de lançamento | Z3: Linha verde = exemplo, apagar
Z4: Linha vermelha = falta campo obrigatório
Z5: Ver folha Validação para lista completa de erros

Sheet Validação
A1: Resumo de Validação — Lista de Preços
A3: Métrica | B3: Valor | C3: Descrição
A4: Total de linhas com dados | B4: =SUMPRODUCT(--((('Lista de Preços'!$A$4:$A$503<>"")+('Lista de Preços'!$B$4:$B$503<>"")+('Lista de Preços'!$C$4:$C$503<>"")+('Lista de Preços'!$D$4:$D$503<>"")+('Lista de Preços'!$E$4:$E$503<>"")+('Lista de Preços'!$F$4:$F$503<>"")+('Lista de Preços'!$G$4:$G$503<>"")+('Lista de Preços'!$H$4:$H$503<>"")+('Lista de Preços'!$I$4:$I$503<>"")+('Lista de Preços'!$J$4:$J$503<>"")+('Lista de Preços'!$K$4:$K$503<>"")+('Lista de Preços'!$L$4:$L$503<>"")+('Lista de Preços'!$M$4:$M$503<>"")+('Lista de Preços'!$N$4:$N$503<>"")+('Lista de Preços'!$O$4:$O$503<>"")+('Lista de Preços'!$P$4:$P$503<>"")+('Lista de Preços'!$Q$4:$Q$503<>"")+('Lista de Preços'!$R$4:$R$503<>"")+('Lista de Preços'!$S$4:$S$503<>"")+('Lista de Preços'!$T$4:$T$503<>"")+('Lista de Preços'!$U$4:$U$503<>"")+('Lista de Preços'!$V$4:$V$503<>"")+('Lista de Preços'!$W$4:$W$503<>""))>0)) -> 0 | C4: Número de linhas na Lista de Preços com pelo menos um campo preenchido (excluindo cabeçalhos e exemplo).
A5: Linhas com campo obrigatório em falta | B5: =COUNTIF($C$15:$C$514,"ERRO") -> 0 | C5: Falta pelo menos um dos campos obrigatórios marcados com * na Lista de Preços.
A6: Preços não numéricos | B6: =COUNTIF($D$15:$D$514,"ERRO") -> 0 | C6: Preço à Farmácia ou Preço ao Público preenchido com texto em vez de número.
A7: Preço à Farmácia > Preço ao Público | B7: =COUNTIF($E$15:$E$514,"ERRO") -> 0 | C7: Não sobra margem para a farmácia — preço à farmácia não pode exceder o PVP.
A8: Datas de validade já passadas | B8: =COUNTIF($F$15:$F$514,"ERRO") -> 0 | C8: Data de Validade preenchida é anterior à data de hoje.
A9: Código de Fornecedor (SKU) duplicado | B9: =COUNTIF($G$15:$G$514,"ERRO") -> 0 | C9: O mesmo Código do Fornecedor aparece em mais do que uma linha.
A10: Desconto fora do intervalo razoável (0%-50%) | B10: =COUNTIF($H$15:$H$514,"ERRO") -> 0 | C10: Desconto do Fornecedor negativo ou acima de 50%.
A11: Linhas totalmente válidas (OK) | B11: =COUNTIF($I$15:$I$514,"OK") -> 0 | C11: Linhas que passaram em todas as verificações acima.
A12: TOTAL DE ERROS A CORRIGIR | B12: =$B$5+$B$6+$B$7+$B$8+$B$9+$B$10 -> 0 | C12: Some as linhas assinaladas como ERRO nas colunas abaixo antes de devolver o ficheiro.
A14: Código Fornecedor (ref.) | B14: Nome Comercial (ref.) | C14: Campo obrigatório em falta | D14: Preço não numérico | E14: Preço Farmácia > PVP | F14: Data de validade passada | G14: SKU duplicado | H14: Desconto fora do intervalo | I14: Estado da Linha
A15: ='Lista de Preços'!$A4 -> 0 | B15: ='Lista de Preços'!$B4 -> 0 | C15: =IF(COUNTA('Lista de Preços'!$A4:$W4)>0,IF((COUNTBLANK('Lista de Preços'!$A4)+COUNTBLANK('Lista de Preços'!$B4)+COUNTBLANK('Lista de Preços'!$C4)+COUNTBLANK('Lista de Preços'!$D4)+COUNTBLANK('Lista de Preços'!$E4)+COUNTBLANK('Lista de Preços'!$F4)+COUNTBLANK('Lista de Preços'!$L4)+COUNTBLANK('Lista de Preços'!$M4)+COUNTBLANK('Lista de Preços'!$P4)+COUNTBLANK('Lista de Preços'!$U4)+COUNTBLANK('Lista de Preços'!$V4))>0,"ERRO","OK"),"") | D15: =IF(COUNTA('Lista de Preços'!$A4:$W4)>0,IF(OR(AND('Lista de Preços'!$L4<>"",NOT(ISNUMBER('Lista de Preços'!$L4))),AND('Lista de Preços'!$M4<>"",NOT(ISNUMBER('Lista de Preços'!$M4)))),"ERRO","OK"),"") | E15: =IF(COUNTA('Lista de Preços'!$A4:$W4)>0,IF(AND(ISNUMBER('Lista de Preços'!$L4),ISNUMBER('Lista de Preços'!$M4),'Lista de Preços'!$L4>'Lista de Preços'!$M4),"ERRO","OK"),"") | F15: =IF(COUNTA('Lista de Preços'!$A4:$W4)>0,IF(AND('Lista de Preços'!$S4<>"",ISNUMBER('Lista de Preços'!$S4),'Lista de Preços'!$S4<TODAY()),"ERRO","OK"),"") | G15: =IF(COUNTA('Lista de Preços'!$A4:$W4)>0,IF(AND('Lista de Preços'!$A4<>"",COUNTIF('Lista de Preços'!$A$4:$A$503,'Lista de Preços'!$A4)>1),"ERRO","OK"),"") | H15: =IF(COUNTA('Lista de Preços'!$A4:$W4)>0,IF(AND('Lista de Preços'!$N4<>"",ISNUMBER('Lista de Preços'!$N4),OR('Lista de Preços'!$N4<0,'Lista de Preços'!$N4>0.5)),"ERRO","OK"),"") | I15: =IF(COUNTA('Lista de Preços'!$A4:$W4)>0,IF(OR($C15="ERRO",$D15="ERRO",$E15="ERRO",$F15="ERRO",$G15="ERRO",$H15="ERRO"),"FALHA","OK"),"")
A16: ='Lista de Preços'!$A5 -> 0 | B16: ='Lista de Preços'!$B5 -> 0 | C16: =IF(COUNTA('Lista de Preços'!$A5:$W5)>0,IF((COUNTBLANK('Lista de Preços'!$A5)+COUNTBLANK('Lista de Preços'!$B5)+COUNTBLANK('Lista de Preços'!$C5)+COUNTBLANK('Lista de Preços'!$D5)+COUNTBLANK('Lista de Preços'!$E5)+COUNTBLANK('Lista de Preços'!$F5)+COUNTBLANK('Lista de Preços'!$L5)+COUNTBLANK('Lista de Preços'!$M5)+COUNTBLANK('Lista de Preços'!$P5)+COUNTBLANK('Lista de Preços'!$U5)+COUNTBLANK('Lista de Preços'!$V5))>0,"ERRO","OK"),"") | D16: =IF(COUNTA('Lista de Preços'!$A5:$W5)>0,IF(OR(AND('Lista de Preços'!$L5<>"",NOT(ISNUMBER('Lista de Preços'!$L5))),AND('Lista de Preços'!$M5<>"",NOT(ISNUMBER('Lista de Preços'!$M5)))),"ERRO","OK"),"") | E16: =IF(COUNTA('Lista de Preços'!$A5:$W5)>0,IF(AND(ISNUMBER('Lista de Preços'!$L5),ISNUMBER('Lista de Preços'!$M5),'Lista de Preços'!$L5>'Lista de Preços'!$M5),"ERRO","OK"),"") | F16: =IF(COUNTA('Lista de Preços'!$A5:$W5)>0,IF(AND('Lista de Preços'!$S5<>"",ISNUMBER('Lista de Preços'!$S5),'Lista de Preços'!$S5<TODAY()),"ERRO","OK"),"") | G16: =IF(COUNTA('Lista de Preços'!$A5:$W5)>0,IF(AND('Lista de Preços'!$A5<>"",COUNTIF('Lista de Preços'!$A$4:$A$503,'Lista de Preços'!$A5)>1),"ERRO","OK"),"") | H16: =IF(COUNTA('Lista de Preços'!$A5:$W5)>0,IF(AND('Lista de Preços'!$N5<>"",ISNUMBER('Lista de Preços'!$N5),OR('Lista de Preços'!$N5<0,'Lista de Preços'!$N5>0.5)),"ERRO","OK"),"") | I16: =IF(COUNTA('Lista de Preços'!$A5:$W5)>0,IF(OR($C16="ERRO",$D16="ERRO",$E16="ERRO",$F16="ERRO",$G16="ERRO",$H16="ERRO"),"FALHA","OK"),"")
A17: ='Lista de Preços'!$A6 -> 0 | B17: ='Lista de Preços'!$B6 -> 0 | C17: =IF(COUNTA('Lista de Preços'!$A6:$W6)>0,IF((COUNTBLANK('Lista de Preços'!$A6)+COUNTBLANK('Lista de Preços'!$B6)+COUNTBLANK('Lista de Preços'!$C6)+COUNTBLANK('Lista de Preços'!$D6)+COUNTBLANK('Lista de Preços'!$E6)+COUNTBLANK('Lista de Preços'!$F6)+COUNTBLANK('Lista de Preços'!$L6)+COUNTBLANK('Lista de Preços'!$M6)+COUNTBLANK('Lista de Preços'!$P6)+COUNTBLANK('Lista de Preços'!$U6)+COUNTBLANK('Lista de Preços'!$V6))>0,"ERRO","OK"),"") | D17: =IF(COUNTA('Lista de Preços'!$A6:$W6)>0,IF(OR(AND('Lista de Preços'!$L6<>"",NOT(ISNUMBER('Lista de Preços'!$L6))),AND('Lista de Preços'!$M6<>"",NOT(ISNUMBER('Lista de Preços'!$M6)))),"ERRO","OK"),"") | E17: =IF(COUNTA('Lista de Preços'!$A6:$W6)>0,IF(AND(ISNUMBER('Lista de Preços'!$L6),ISNUMBER('Lista de Preços'!$M6),'Lista de Preços'!$L6>'Lista de Preços'!$M6),"ERRO","OK"),"") | F17: =IF(COUNTA('Lista de Preços'!$A6:$W6)>0,IF(AND('Lista de Preços'!$S6<>"",ISNUMBER('Lista de Preços'!$S6),'Lista de Preços'!$S6<TODAY()),"ERRO","OK"),"") | G17: =IF(COUNTA('Lista de Preços'!$A6:$W6)>0,IF(AND('Lista de Preços'!$A6<>"",COUNTIF('Lista de Preços'!$A$4:$A$503,'Lista de Preços'!$A6)>1),"ERRO","OK"),"") | H17: =IF(COUNTA('Lista de Preços'!$A6:$W6)>0,IF(AND('Lista de Preços'!$N6<>"",ISNUMBER('Lista de Preços'!$N6),OR('Lista de Preços'!$N6<0,'Lista de Preços'!$N6>0.5)),"ERRO","OK"),"") | I17: =IF(COUNTA('Lista de Preços'!$A6:$W6)>0,IF(OR($C17="ERRO",$D17="ERRO",$E17="ERRO",$F17="ERRO",$G17="ERRO",$H17="ERRO"),"FALHA","OK"),"")
A18: ='Lista de Preços'!$A7 -> 0 | B18: ='Lista de Preços'!$B7 -> 0 | C18: =IF(COUNTA('Lista de Preços'!$A7:$W7)>0,IF((COUNTBLANK('Lista de Preços'!$A7)+COUNTBLANK('Lista de Preços'!$B7)+COUNTBLANK('Lista de Preços'!$C7)+COUNTBLANK('Lista de Preços'!$D7)+COUNTBLANK('Lista de Preços'!$E7)+COUNTBLANK('Lista de Preços'!$F7)+COUNTBLANK('Lista de Preços'!$L7)+COUNTBLANK('Lista de Preços'!$M7)+COUNTBLANK('Lista de Preços'!$P7)+COUNTBLANK('Lista de Preços'!$U7)+COUNTBLANK('Lista de Preços'!$V7))>0,"ERRO","OK"),"") | D18: =IF(COUNTA('Lista de Preços'!$A7:$W7)>0,IF(OR(AND('Lista de Preços'!$L7<>"",NOT(ISNUMBER('Lista de Preços'!$L7))),AND('Lista de Preços'!$M7<>"",NOT(ISNUMBER('Lista de Preços'!$M7)))),"ERRO","OK"),"") | E18: =IF(COUNTA('Lista de Preços'!$A7:$W7)>0,IF(AND(ISNUMBER('Lista de Preços'!$L7),ISNUMBER('Lista de Preços'!$M7),'Lista de Preços'!$L7>'Lista de Preços'!$M7),"ERRO","OK"),"") | F18: =IF(COUNTA('Lista de Preços'!$A7:$W7)>0,IF(AND('Lista de Preços'!$S7<>"",ISNUMBER('Lista de Preços'!$S7),'Lista de Preços'!$S7<TODAY()),"ERRO","OK"),"") | G18: =IF(COUNTA('Lista de Preços'!$A7:$W7)>0,IF(AND('Lista de Preços'!$A7<>"",COUNTIF('Lista de Preços'!$A$4:$A$503,'Lista de Preços'!$A7)>1),"ERRO","OK"),"") | H18: =IF(COUNTA('Lista de Preços'!$A7:$W7)>0,IF(AND('Lista de Preços'!$N7<>"",ISNUMBER('Lista de Preços'!$N7),OR('Lista de Preços'!$N7<0,'Lista de Preços'!$N7>0.5)),"ERRO","OK"),"") | I18: =IF(COUNTA('Lista de Preços'!$A7:$W7)>0,IF(OR($C18="ERRO",$D18="ERRO",$E18="ERRO",$F18="ERRO",$G18="ERRO",$H18="ERRO"),"FALHA","OK"),"")
A19: ='Lista de Preços'!$A8 -> 0 | B19: ='Lista de Preços'!$B8 -> 0 | C19: =IF(COUNTA('Lista de Preços'!$A8:$W8)>0,IF((COUNTBLANK('Lista de Preços'!$A8)+COUNTBLANK('Lista de Preços'!$B8)+COUNTBLANK('Lista de Preços'!$C8)+COUNTBLANK('Lista de Preços'!$D8)+COUNTBLANK('Lista de Preços'!$E8)+COUNTBLANK('Lista de Preços'!$F8)+COUNTBLANK('Lista de Preços'!$L8)+COUNTBLANK('Lista de Preços'!$M8)+COUNTBLANK('Lista de Preços'!$P8)+COUNTBLANK('Lista de Preços'!$U8)+COUNTBLANK('Lista de Preços'!$V8))>0,"ERRO","OK"),"") | D19: =IF(COUNTA('Lista de Preços'!$A8:$W8)>0,IF(OR(AND('Lista de Preços'!$L8<>"",NOT(ISNUMBER('Lista de Preços'!$L8))),AND('Lista de Preços'!$M8<>"",NOT(ISNUMBER('Lista de Preços'!$M8)))),"ERRO","OK"),"") | E19: =IF(COUNTA('Lista de Preços'!$A8:$W8)>0,IF(AND(ISNUMBER('Lista de Preços'!$L8),ISNUMBER('Lista de Preços'!$M8),'Lista de Preços'!$L8>'Lista de Preços'!$M8),"ERRO","OK"),"") | F19: =IF(COUNTA('Lista de Preços'!$A8:$W8)>0,IF(AND('Lista de Preços'!$S8<>"",ISNUMBER('Lista de Preços'!$S8),'Lista de Preços'!$S8<TODAY()),"ERRO","OK"),"") | G19: =IF(COUNTA('Lista de Preços'!$A8:$W8)>0,IF(AND('Lista de Preços'!$A8<>"",COUNTIF('Lista de Preços'!$A$4:$A$503,'Lista de Preços'!$A8)>1),"ERRO","OK"),"") | H19: =IF(COUNTA('Lista de Preços'!$A8:$W8)>0,IF(AND('Lista de Preços'!$N8<>"",ISNUMBER('Lista de Preços'!$N8),OR('Lista de Preços'!$N8<0,'Lista de Preços'!$N8>0.5)),"ERRO","OK"),"") | I19: =IF(COUNTA('Lista de Preços'!$A8:$W8)>0,IF(OR($C19="ERRO",$D19="ERRO",$E19="ERRO",$F19="ERRO",$G19="ERRO",$H19="ERRO"),"FALHA","OK"),"")
A20: ='Lista de Preços'!$A9 -> 0 | B20: ='Lista de Preços'!$B9 -> 0 | C20: =IF(COUNTA('Lista de Preços'!$A9:$W9)>0,IF((COUNTBLANK('Lista de Preços'!$A9)+COUNTBLANK('Lista de Preços'!$B9)+COUNTBLANK('Lista de Preços'!$C9)+COUNTBLANK('Lista de Preços'!$D9)+COUNTBLANK('Lista de Preços'!$E9)+COUNTBLANK('Lista de Preços'!$F9)+COUNTBLANK('Lista de Preços'!$L9)+COUNTBLANK('Lista de Preços'!$M9)+COUNTBLANK('Lista de Preços'!$P9)+COUNTBLANK('Lista de Preços'!$U9)+COUNTBLANK('Lista de Preços'!$V9))>0,"ERRO","OK"),"") | D20: =IF(COUNTA('Lista de Preços'!$A9:$W9)>0,IF(OR(AND('Lista de Preços'!$L9<>"",NOT(ISNUMBER('Lista de Preços'!$L9))),AND('Lista de Preços'!$M9<>"",NOT(ISNUMBER('Lista de Preços'!$M9)))),"ERRO","OK"),"") | E20: =IF(COUNTA('Lista de Preços'!$A9:$W9)>0,IF(AND(ISNUMBER('Lista de Preços'!$L9),ISNUMBER('Lista de Preços'!$M9),'Lista de Preços'!$L9>'Lista de Preços'!$M9),"ERRO","OK"),"") | F20: =IF(COUNTA('Lista de Preços'!$A9:$W9)>0,IF(AND('Lista de Preços'!$S9<>"",ISNUMBER('Lista de Preços'!$S9),'Lista de Preços'!$S9<TODAY()),"ERRO","OK"),"") | G20: =IF(COUNTA('Lista de Preços'!$A9:$W9)>0,IF(AND('Lista de Preços'!$A9<>"",COUNTIF('Lista de Preços'!$A$4:$A$503,'Lista de Preços'!$A9)>1),"ERRO","OK"),"") | H20: =IF(COUNTA('Lista de Preços'!$A9:$W9)>0,IF(AND('Lista de Preços'!$N9<>"",ISNUMBER('Lista de Preços'!$N9),OR('Lista de Preços'!$N9<0,'Lista de Preços'!$N9>0.5)),"ERRO","OK"),"") | I20: =IF(COUNTA('Lista de Preços'!$A9:$W9)>0,IF(OR($C20="ERRO",$D20="ERRO",$E20="ERRO",$F20="ERRO",$G20="ERRO",$H20="ERRO"),"FALHA","OK"),"")
A21: ='Lista de Preços'!$A10 -> 0 | B21: ='Lista de Preços'!$B10 -> 0 | C21: =IF(COUNTA('Lista de Preços'!$A10:$W10)>0,IF((COUNTBLANK('Lista de Preços'!$A10)+COUNTBLANK('Lista de Preços'!$B10)+COUNTBLANK('Lista de Preços'!$C10)+COUNTBLANK('Lista de Preços'!$D10)+COUNTBLANK('Lista de Preços'!$E10)+COUNTBLANK('Lista de Preços'!$F10)+COUNTBLANK('Lista de Preços'!$L10)+COUNTBLANK('Lista de Preços'!$M10)+COUNTBLANK('Lista de Preços'!$P10)+COUNTBLANK('Lista de Preços'!$U10)+COUNTBLANK('Lista de Preços'!$V10))>0,"ERRO","OK"),"") | D21: =IF(COUNTA('Lista de Preços'!$A10:$W10)>0,IF(OR(AND('Lista de Preços'!$L10<>"",NOT(ISNUMBER('Lista de Preços'!$L10))),AND('Lista de Preços'!$M10<>"",NOT(ISNUMBER('Lista de Preços'!$M10)))),"ERRO","OK"),"") | E21: =IF(COUNTA('Lista de Preços'!$A10:$W10)>0,IF(AND(ISNUMBER('Lista de Preços'!$L10),ISNUMBER('Lista de Preços'!$M10),'Lista de Preços'!$L10>'Lista de Preços'!$M10),"ERRO","OK"),"") | F21: =IF(COUNTA('Lista de Preços'!$A10:$W10)>0,IF(AND('Lista de Preços'!$S10<>"",ISNUMBER('Lista de Preços'!$S10),'Lista de Preços'!$S10<TODAY()),"ERRO","OK"),"") | G21: =IF(COUNTA('Lista de Preços'!$A10:$W10)>0,IF(AND('Lista de Preços'!$A10<>"",COUNTIF('Lista de Preços'!$A$4:$A$503,'Lista de Preços'!$A10)>1),"ERRO","OK"),"") | H21: =IF(COUNTA('Lista de Preços'!$A10:$W10)>0,IF(AND('Lista de Preços'!$N10<>"",ISNUMBER('Lista de Preços'!$N10),OR('Lista de Preços'!$N10<0,'Lista de Preços'!$N10>0.5)),"ERRO","OK"),"") | I21: =IF(COUNTA('Lista de Preços'!$A10:$W10)>0,IF(OR($C21="ERRO",$D21="ERRO",$E21="ERRO",$F21="ERRO",$G21="ERRO",$H21="ERRO"),"FALHA","OK"),"")
A22: ='Lista de Preços'!$A11 -> 0 | B22: ='Lista de Preços'!$B11 -> 0 | C22: =IF(COUNTA('Lista de Preços'!$A11:$W11)>0,IF((COUNTBLANK('Lista de Preços'!$A11)+COUNTBLANK('Lista de Preços'!$B11)+COUNTBLANK('Lista de Preços'!$C11)+COUNTBLANK('Lista de Preços'!$D11)+COUNTBLANK('Lista de Preços'!$E11)+COUNTBLANK('Lista de Preços'!$F11)+COUNTBLANK('Lista de Preços'!$L11)+COUNTBLANK('Lista de Preços'!$M11)+COUNTBLANK('Lista de Preços'!$P11)+COUNTBLANK('Lista de Preços'!$U11)+COUNTBLANK('Lista de Preços'!$V11))>0,"ERRO","OK"),"") | D22: =IF(COUNTA('Lista de Preços'!$A11:$W11)>0,IF(OR(AND('Lista de Preços'!$L11<>"",NOT(ISNUMBER('Lista de Preços'!$L11))),AND('Lista de Preços'!$M11<>"",NOT(ISNUMBER('Lista de Preços'!$M11)))),"ERRO","OK"),"") | E22: =IF(COUNTA('Lista de Preços'!$A11:$W11)>0,IF(AND(ISNUMBER('Lista de Preços'!$L11),ISNUMBER('Lista de Preços'!$M11),'Lista de Preços'!$L11>'Lista de Preços'!$M11),"ERRO","OK"),"") | F22: =IF(COUNTA('Lista de Preços'!$A11:$W11)>0,IF(AND('Lista de Preços'!$S11<>"",ISNUMBER('Lista de Preços'!$S11),'Lista de Preços'!$S11<TODAY()),"ERRO","OK"),"") | G22: =IF(COUNTA('Lista de Preços'!$A11:$W11)>0,IF(AND('Lista de Preços'!$A11<>"",COUNTIF('Lista de Preços'!$A$4:$A$503,'Lista de Preços'!$A11)>1),"ERRO","OK"),"") | H22: =IF(COUNTA('Lista de Preços'!$A11:$W11)>0,IF(AND('Lista de Preços'!$N11<>"",ISNUMBER('Lista de Preços'!$N11),OR('Lista de Preços'!$N11<0,'Lista de Preços'!$N11>0.5)),"ERRO","OK"),"") | I22: =IF(COUNTA('Lista de Preços'!$A11:$W11)>0,IF(OR($C22="ERRO",$D22="ERRO",$E22="ERRO",$F22="ERRO",$G22="ERRO",$H22="ERRO"),"FALHA","OK"),"")
A23: ='Lista de Preços'!$A12 -> 0 | B23: ='Lista de Preços'!$B12 -> 0 | C23: =IF(COUNTA('Lista de Preços'!$A12:$W12)>0,IF((COUNTBLANK('Lista de Preços'!$A12)+COUNTBLANK('Lista de Preços'!$B12)+COUNTBLANK('Lista de Preços'!$C12)+COUNTBLANK('Lista de Preços'!$D12)+COUNTBLANK('Lista de Preços'!$E12)+COUNTBLANK('Lista de Preços'!$F12)+COUNTBLANK('Lista de Preços'!$L12)+COUNTBLANK('Lista de Preços'!$M12)+COUNTBLANK('Lista de Preços'!$P12)+COUNTBLANK('Lista de Preços'!$U12)+COUNTBLANK('Lista de Preços'!$V12))>0,"ERRO","OK"),"") | D23: =IF(COUNTA('Lista de Preços'!$A12:$W12)>0,IF(OR(AND('Lista de Preços'!$L12<>"",NOT(ISNUMBER('Lista de Preços'!$L12))),AND('Lista de Preços'!$M12<>"",NOT(ISNUMBER('Lista de Preços'!$M12)))),"ERRO","OK"),"") | E23: =IF(COUNTA('Lista de Preços'!$A12:$W12)>0,IF(AND(ISNUMBER('Lista de Preços'!$L12),ISNUMBER('Lista de Preços'!$M12),'Lista de Preços'!$L12>'Lista de Preços'!$M12),"ERRO","OK"),"") | F23: =IF(COUNTA('Lista de Preços'!$A12:$W12)>0,IF(AND('Lista de Preços'!$S12<>"",ISNUMBER('Lista de Preços'!$S12),'Lista de Preços'!$S12<TODAY()),"ERRO","OK"),"") | G23: =IF(COUNTA('Lista de Preços'!$A12:$W12)>0,IF(AND('Lista de Preços'!$A12<>"",COUNTIF('Lista de Preços'!$A$4:$A$503,'Lista de Preços'!$A12)>1),"ERRO","OK"),"") | H23: =IF(COUNTA('Lista de Preços'!$A12:$W12)>0,IF(AND('Lista de Preços'!$N12<>"",ISNUMBER('Lista de Preços'!$N12),OR('Lista de Preços'!$N12<0,'Lista de Preços'!$N12>0.5)),"ERRO","OK"),"") | I23: =IF(COUNTA('Lista de Preços'!$A12:$W12)>0,IF(OR($C23="ERRO",$D23="ERRO",$E23="ERRO",$F23="ERRO",$G23="ERRO",$H23="ERRO"),"FALHA","OK"),"")
A24: ='Lista de Preços'!$A13 -> 0 | B24: ='Lista de Preços'!$B13 -> 0 | C24: =IF(COUNTA('Lista de Preços'!$A13:$W13)>0,IF((COUNTBLANK('Lista de Preços'!$A13)+COUNTBLANK('Lista de Preços'!$B13)+COUNTBLANK('Lista de Preços'!$C13)+COUNTBLANK('Lista de Preços'!$D13)+COUNTBLANK('Lista de Preços'!$E13)+COUNTBLANK('Lista de Preços'!$F13)+COUNTBLANK('Lista de Preços'!$L13)+COUNTBLANK('Lista de Preços'!$M13)+COUNTBLANK('Lista de Preços'!$P13)+COUNTBLANK('Lista de Preços'!$U13)+COUNTBLANK('Lista de Preços'!$V13))>0,"ERRO","OK"),"") | D24: =IF(COUNTA('Lista de Preços'!$A13:$W13)>0,IF(OR(AND('Lista de Preços'!$L13<>"",NOT(ISNUMBER('Lista de Preços'!$L13))),AND('Lista de Preços'!$M13<>"",NOT(ISNUMBER('Lista de Preços'!$M13)))),"ERRO","OK"),"") | E24: =IF(COUNTA('Lista de Preços'!$A13:$W13)>0,IF(AND(ISNUMBER('Lista de Preços'!$L13),ISNUMBER('Lista de Preços'!$M13),'Lista de Preços'!$L13>'Lista de Preços'!$M13),"ERRO","OK"),"") | F24: =IF(COUNTA('Lista de Preços'!$A13:$W13)>0,IF(AND('Lista de Preços'!$S13<>"",ISNUMBER('Lista de Preços'!$S13),'Lista de Preços'!$S13<TODAY()),"ERRO","OK"),"") | G24: =IF(COUNTA('Lista de Preços'!$A13:$W13)>0,IF(AND('Lista de Preços'!$A13<>"",COUNTIF('Lista de Preços'!$A$4:$A$503,'Lista de Preços'!$A13)>1),"ERRO","OK"),"") | H24: =IF(COUNTA('Lista de Preços'!$A13:$W13)>0,IF(AND('Lista de Preços'!$N13<>"",ISNUMBER('Lista de Preços'!$N13),OR('Lista de Preços'!$N13<0,'Lista de Preços'!$N13>0.5)),"ERRO","OK"),"") | I24: =IF(COUNTA('Lista de Preços'!$A13:$W13)>0,IF(OR($C24="ERRO",$D24="ERRO",$E24="ERRO",$F24="ERRO",$G24="ERRO",$H24="ERRO"),"FALHA","OK"),"")
A25: ='Lista de Preços'!$A14 -> 0 | B25: ='Lista de Preços'!$B14 -> 0 | C25: =IF(COUNTA('Lista de Preços'!$A14:$W14)>0,IF((COUNTBLANK('Lista de Preços'!$A14)+COUNTBLANK('Lista de Preços'!$B14)+COUNTBLANK('Lista de Preços'!$C14)+COUNTBLANK('Lista de Preços'!$D14)+COUNTBLANK('Lista de Preços'!$E14)+COUNTBLANK('Lista de Preços'!$F14)+COUNTBLANK('Lista de Preços'!$L14)+COUNTBLANK('Lista de Preços'!$M14)+COUNTBLANK('Lista de Preços'!$P14)+COUNTBLANK('Lista de Preços'!$U14)+COUNTBLANK('Lista de Preços'!$V14))>0,"ERRO","OK"),"") | D25: =IF(COUNTA('Lista de Preços'!$A14:$W14)>0,IF(OR(AND('Lista de Preços'!$L14<>"",NOT(ISNUMBER('Lista de Preços'!$L14))),AND('Lista de Preços'!$M14<>"",NOT(ISNUMBER('Lista de Preços'!$M14)))),"ERRO","OK"),"") | E25: =IF(COUNTA('Lista de Preços'!$A14:$W14)>0,IF(AND(ISNUMBER('Lista de Preços'!$L14),ISNUMBER('Lista de Preços'!$M14),'Lista de Preços'!$L14>'Lista de Preços'!$M14),"ERRO","OK"),"") | F25: =IF(COUNTA('Lista de Preços'!$A14:$W14)>0,IF(AND('Lista de Preços'!$S14<>"",ISNUMBER('Lista de Preços'!$S14),'Lista de Preços'!$S14<TODAY()),"ERRO","OK"),"") | G25: =IF(COUNTA('Lista de Preços'!$A14:$W14)>0,IF(AND('Lista de Preços'!$A14<>"",COUNTIF('Lista de Preços'!$A$4:$A$503,'Lista de Preços'!$A14)>1),"ERRO","OK"),"") | H25: =IF(COUNTA('Lista de Preços'!$A14:$W14)>0,IF(AND('Lista de Preços'!$N14<>"",ISNUMBER('Lista de Preços'!$N14),OR('Lista de Preços'!$N14<0,'Lista de Preços'!$N14>0.5)),"ERRO","OK"),"") | I25: =IF(COUNTA('Lista de Preços'!$A14:$W14)>0,IF(OR($C25="ERRO",$D25="ERRO",$E25="ERRO",$F25="ERRO",$G25="ERRO",$H25="ERRO"),"FALHA","OK"),"")
A26: ='Lista de Preços'!$A15 -> 0 | B26: ='Lista de Preços'!$B15 -> 0 | C26: =IF(COUNTA('Lista de Preços'!$A15:$W15)>0,IF((COUNTBLANK('Lista de Preços'!$A15)+COUNTBLANK('Lista de Preços'!$B15)+COUNTBLANK('Lista de Preços'!$C15)+COUNTBLANK('Lista de Preços'!$D15)+COUNTBLANK('Lista de Preços'!$E15)+COUNTBLANK('Lista de Preços'!$F15)+COUNTBLANK('Lista de Preços'!$L15)+COUNTBLANK('Lista de Preços'!$M15)+COUNTBLANK('Lista de Preços'!$P15)+COUNTBLANK('Lista de Preços'!$U15)+COUNTBLANK('Lista de Preços'!$V15))>0,"ERRO","OK"),"") | D26: =IF(COUNTA('Lista de Preços'!$A15:$W15)>0,IF(OR(AND('Lista de Preços'!$L15<>"",NOT(ISNUMBER('Lista de Preços'!$L15))),AND('Lista de Preços'!$M15<>"",NOT(ISNUMBER('Lista de Preços'!$M15)))),"ERRO","OK"),"") | E26: =IF(COUNTA('Lista de Preços'!$A15:$W15)>0,IF(AND(ISNUMBER('Lista de Preços'!$L15),ISNUMBER('Lista de Preços'!$M15),'Lista de Preços'!$L15>'Lista de Preços'!$M15),"ERRO","OK"),"") | F26: =IF(COUNTA('Lista de Preços'!$A15:$W15)>0,IF(AND('Lista de Preços'!$S15<>"",ISNUMBER('Lista de Preços'!$S15),'Lista de Preços'!$S15<TODAY()),"ERRO","OK"),"") | G26: =IF(COUNTA('Lista de Preços'!$A15:$W15)>0,IF(AND('Lista de Preços'!$A15<>"",COUNTIF('Lista de Preços'!$A$4:$A$503,'Lista de Preços'!$A15)>1),"ERRO","OK"),"") | H26: =IF(COUNTA('Lista de Preços'!$A15:$W15)>0,IF(AND('Lista de Preços'!$N15<>"",ISNUMBER('Lista de Preços'!$N15),OR('Lista de Preços'!$N15<0,'Lista de Preços'!$N15>0.5)),"ERRO","OK"),"") | I26: =IF(COUNTA('Lista de Preços'!$A15:$W15)>0,IF(OR($C26="ERRO",$D26="ERRO",$E26="ERRO",$F26="ERRO",$G26="ERRO",$H26="ERRO"),"FALHA","OK"),"")
... A514: ='Lista de Preços'!$A503 -> 0 | B514: ='Lista de Preços'!$B503 -> 0 | C514: =IF(COUNTA('Lista de Preços'!$A503:$W503)>0,IF((COUNTBLANK('Lista de Preços'!$A503)+COUNTBLANK('Lista de Preços'!$B503)+COUNTBLANK('Lista de Preços'!$C503)+COUNTBLANK('Lista de Preços'!$D503)+COUNTBLANK('Lista de Preços'!$E503)+COUNTBLANK('Lista de Preços'!$F503)+COUNTBLANK('Lista de Preços'!$L503)+COUNTBLANK('Lista de Preços'!$M503)+COUNTBLANK('Lista de Preços'!$P503)+COUNTBLANK('Lista de Preços'!$U503)+COUNTBLANK('Lista de Preços'!$V503))>0,"ERRO","OK"),"") | D514: =IF(COUNTA('Lista de Preços'!$A503:$W503)>0,IF(OR(AND('Lista de Preços'!$L503<>"",NOT(ISNUMBER('Lista de Preços'!$L503))),AND('Lista de Preços'!$M503<>"",NOT(ISNUMBER('Lista de Preços'!$M503)))),"ERRO","OK"),"") | E514: =IF(COUNTA('Lista de Preços'!$A503:$W503)>0,IF(AND(ISNUMBER('Lista de Preços'!$L503),ISNUMBER('Lista de Preços'!$M503),'Lista de Preços'!$L503>'Lista de Preços'!$M503),"ERRO","OK"),"") | F514: =IF(COUNTA('Lista de Preços'!$A503:$W503)>0,IF(AND('Lista de Preços'!$S503<>"",ISNUMBER('Lista de Preços'!$S503),'Lista de Preços'!$S503<TODAY()),"ERRO","OK"),"") | G514: =IF(COUNTA('Lista de Preços'!$A503:$W503)>0,IF(AND('Lista de Preços'!$A503<>"",COUNTIF('Lista de Preços'!$A$4:$A$503,'Lista de Preços'!$A503)>1),"ERRO","OK"),"") | H514: =IF(COUNTA('Lista de Preços'!$A503:$W503)>0,IF(AND('Lista de Preços'!$N503<>"",ISNUMBER('Lista de Preços'!$N503),OR('Lista de Preços'!$N503<0,'Lista de Preços'!$N503>0.5)),"ERRO","OK"),"") | I514: =IF(COUNTA('Lista de Preços'!$A503:$W503)>0,IF(OR($C514="ERRO",$D514="ERRO",$E514="ERRO",$F514="ERRO",$G514="ERRO",$H514="ERRO"),"FALHA","OK"),"")

Sheet Dicionário
A1: Rótulo (Português) | B1: Identificador (English) | C1: التسمية (عربي) | D1: Tipo | E1: Obrigatório / Opcional | F1: Regras | G1: Exemplo
A2: Código do Fornecedor (SKU) | B2: vendor_sku | C2: رمز المورد (SKU) | D2: Texto | E2: Obrigatório | F2: Texto/código único e estável por produto. É a CHAVE usada para actualizar preços em envios futuros — não mude o código de um produto já enviado antes. | G2: AH-AMX500-24
A3: Nome Comercial | B3: product_name_brand | C3: الاسم التجاري | D3: Texto | E3: Obrigatório | F3: Nome comercial/de marca tal como aparece na embalagem. | G3: Amoxil 500mg
A4: Nome Científico (DCI) | B4: product_name_inn | C4: الاسم العلمي (DCI/INN) | D4: Texto | E4: Obrigatório | F4: Denominação Comum Internacional (DCI/INN). Obrigatório mesmo quando igual ao nome comercial. | G4: Amoxicilina
A5: Forma Farmacêutica | B5: form | C5: الشكل الصيدلاني | D5: Lista (menu suspenso) | E5: Obrigatório | F5: Escolher da lista (menu suspenso). Opções: Comprimido, Cápsula, Xarope, Injectável, Pomada, Creme, Gotas, Supositório, Pó, Solução, Outro. | G5: Cápsula
A6: Dosagem | B6: strength | C6: التركيز/الجرعة | D6: Texto | E6: Obrigatório | F6: Texto livre, com unidade incluída (ex: 500mg, 250mg/5ml). | G6: 500mg
A7: Unidades por Embalagem | B7: pack_size | C7: عدد الوحدات في العبوة | D7: Número (inteiro) | E7: Obrigatório | F7: Número inteiro positivo (quantas unidades/comprimidos/ml existem numa embalagem de venda). | G7: 24
A8: Unidade da Embalagem | B8: pack_unit | C8: وحدة العبوة | D8: Lista (menu suspenso) | E8: Opcional | F8: Escolher da lista. Opcional mas recomendado — sem isto o sistema assume 'unidades'. Opções: comprimidos, cápsulas, ml, g, ampolas, frascos, unidades. | G8: cápsulas
A9: Fabricante | B9: manufacturer | C9: الشركة المصنعة | D9: Texto | E9: Opcional | F9: Opcional, mas melhora a precisão do pareamento com o Índice quando há várias marcas do mesmo genérico. | G9: GlaxoSmithKline
A10: País de Origem | B10: country_of_origin | C10: بلد المنشأ | D10: Texto | E10: Opcional | F10: Opcional. | G10: Índia
A11: Número AIM | B11: aim_number | C11: رقم التسجيل (AIM) | D11: Texto | E11: Opcional | F11: Número de Autorização de Introdução no Mercado (ANARME), quando exista. Deixe em branco se não souber. | G11: AIM-MZ-004521
A12: Código de Barras | B12: barcode | C12: الباركود | D12: Texto | E12: Opcional | F12: EAN/UPC da embalagem, se existir. | G12: 7891234567895
... A24: Observações | B24: notes | C24: ملاحظات | D24: Texto | E24: Opcional | F24: Opcional, texto livre. | G24: Promoção de lançamento
A26: Nota: para produtos medicamentosos com preço regulado pelo Estado (Diploma Ministerial 21/2017), o Preço ao Público (PVP) final é o do Índice de Medicamentos, não o valor desta folha — ver a especificação de importação para o processo completo.
